Workbook

Sheet Assumptions
A1: Cheerio Assist — Operational & Financial Model Assumptions
A2: Baseline assumptions for 5,000 active businesses scaling WhatsApp API support. Clearly marked as provisional.
A4: Assumption Parameter | B4: Value | C4: Unit | D4: Type / Status | E4: Source / Rationale
A5: Active Businesses Base | B5: 5000 | C5: Accounts | D5: Assignment Specification | E5: Provided in prompt context
A6: Monthly Support Queries per Business | B6: 0.8 | C6: Queries/Biz | D6: Provisional Assumption | E6: Estimated based on B2B SaaS onboarding benchmarks
A7: Share of Inbound Queries Eligible for Self-Service | B7: 0.7 | C7: 0.0% | D7: Provisional Assumption | E7: Top 5 issues (WhatsApp, Templates, Flows, Integrations)
A8: Target Resolution Rate on Eligible Queries | B8: 0.65 | C8: 0.0% | D8: 3-Month Provisional Target | E8: Expected autonomous resolution without human intervention
A9: Average Input Tokens per AI Interaction | B9: 850 | C9: Tokens | D9: Engineering Estimate | E9: Includes system prompt, user query, and diagnostic history
A10: Average Output Tokens per AI Interaction | B10: 350 | C10: Tokens | D10: Engineering Estimate | E10: Concise, plain-English guidance and step instructions
A11: LLM Model Input Price per 1M Tokens ($) | B11: 0.15 | C11: $#,##0.00 | D11: Verified Public Price | E11: OpenAI GPT-4o-mini ($0.15/1M input) / Gemini 1.5 Flash
A12: LLM Model Output Price per 1M Tokens ($) | B12: 0.6 | C12: $#,##0.00 | D12: Verified Public Price | E12: OpenAI GPT-4o-mini ($0.60/1M output) / Gemini 1.5 Flash
A13: Cloud Infrastructure, Search & Monitoring / Mo ($) | B13: 250 | C13: $#,##0.00 | D13: Operational Estimate | E13: Vector indexing, logging, serverless hosting (Vercel/AWS)
A14: Blended Human Support Cost per Ticket ($) | B14: 8.5 | C14: $#,##0.00 | D14: Industry Benchmark | E14: Average cost of Tier 1/2 human support agent time (15-20 min)
A15: Proposed Premium Add-on Price ($/mo) | B15: 19 | C15: $#,##0.00 | D15: Proposed Pricing Model | E15: Optional 'Cheerio Assist Pro' tier with custom CRM syncing
A16: Assumed Adoption Rate for Paid Add-on | B16: 0.15 | C16: 0.0% | D16: Conservative Assumption | E16: 15% adoption among 5,000 businesses (750 paying orgs)
A18: Note: Model prices based on OpenAI GPT-4o-mini / Gemini 1.5 Flash official documentation (https://openai.com/api/pricing/). All other values are editable scenario inputs.

Sheet Volume & Resolution
A1: Monthly Support Query Volume & Resolution Funnel
A2: Formulas strictly reference the Assumptions sheet. Distinguishes eligible queries from automated resolutions.
A4: Funnel Metric | B4: Formula / Source | C4: Monthly Volume | D4: Share of Total | E4: Operational Definition & Rationale
A5: Total Monthly Inbound Support Queries | B5: =Assumptions!B5*Assumptions!B6 | C5: =Assumptions!B5*Assumptions!B6 | D5: =C5/C5 | E5: 5,000 businesses * 0.8 queries/month
A6: Queries Eligible for Self-Service Automation | B6: =C5*Assumptions!B7 | C6: =C5*Assumptions!B7 | D6: =C6/C$5 | E6: Issues covered by WhatsApp, Template, Bot, and Integration copilot
A7: Ineligible Complex / Custom Queries | B7: =C5-C6 | C7: =C5-C6 | D7: =C7/C$5 | E7: Complex bugs, legal, or bespoke enterprise requests (Direct to Human)
A8: Queries Successfully Resolved Autonomously | B8: =C6*Assumptions!B8 | C8: =C6*Assumptions!B8 | D8: =C8/C$5 | E8: Resolved via diagnostic checklist & AI Copilot without agent ticket
A9: Queries Escalated to Human Support (From Eligible) | B9: =C6-C8 | C9: =C6-C8 | D9: =C9/C$5 | E9: Failed troubleshooting, account-level locks, or explicit escalation
A10: Total Residual Queries Handled by Humans | B10: =C7+C9 | C10: =C7+C9 | D10: =C10/C$5 | E10: Sum of ineligible inbound queries + escalated eligible queries
A12: Key Performance Rates:
A13: Overall Autonomous Resolution Rate (% of All Inbound) | C13: =C8/C5 | E13: 1,820 resolved / 4,000 total inbound = 45.5% net support workload automated
A14: Effective Self-Service Resolution Rate (% of Eligible) | C14: =C8/C6 | E14: 1,820 resolved / 2,800 eligible = 65.0% success rate on eligible workflows

Sheet Running Cost
A1: Cheerio Assist — Recurring Monthly Operating Cost Model
A2: Calculates token consumption, API spend, infrastructure, and blended per-resolution economics.
A4: Cost Component | B4: Formula / Derivation | C4: Unit Cost | D4: Monthly Total ($) | E4: Cost Modeling Notes
A5: Input Token Cost per AI Interaction | B5: =(Assumptions!B9/1000000)*Assumptions!B11 | C5: =(Assumptions!B9/1000000)*Assumptions!B11 | D5: =C5*'Volume & Resolution'!C6 | E5: 850 tokens * $0.15/1M tokens = $0.0001275 per interaction
A6: Output Token Cost per AI Interaction | B6: =(Assumptions!B10/1000000)*Assumptions!B12 | C6: =(Assumptions!B10/1000000)*Assumptions!B12 | D6: =C6*'Volume & Resolution'!C6 | E6: 350 tokens * $0.60/1M tokens = $0.0002100 per interaction
A7: Total AI Model Cost per Interaction | B7: =C5+C6 | C7: =C5+C6 | D7: =D5+D6 | E7: Blended token cost per interaction = $0.0003375
A8: Total Monthly AI Model Inference Cost | B8: =D7 | D8: =D7 | E8: Inference across 2,800 eligible customer sessions
A9: Platform Infrastructure, Search & Logging | B9: =Assumptions!B13 | D9: =Assumptions!B13 | E9: Vercel / AWS serverless, Vector search cache, monitoring
A10: Total Monthly Solution Operating Cost | B10: =D8+D9 | D10: =D8+D9 | E10: Sum of monthly AI token inference + fixed cloud infrastructure
A11: Average Cost per Incoming Support Query | B11: =D10/'Volume & Resolution'!C5 | D11: =D10/'Volume & Resolution'!C5 | E11: Total operating cost / 4,000 incoming support queries
A12: Cost per Successfully Automated Resolution | B12: =D10/'Volume & Resolution'!C8 | D12: =D10/'Volume & Resolution'!C8 | E12: Total operating cost / 1,820 resolved queries ($0.138 per resolution!)

Sheet Billing & Margin
A1: Cheerio Assist — Monetization Strategy & Margin Comparison
A2: Evaluates Free Core Feature vs Usage Credits vs Paid Add-on. Recommends hybrid approach.
A4: Commercial Model | B4: Proposed Price | C4: User Adoption Friction | D4: Primary Strategic Value | E4: Product Recommendation
A5: 1. Free Self-Service (Core Included) | B5: $0.00 / mo | C5: Zero Friction (100% Onboarding Access) | D5: Prevents early churn, boosts WhatsApp onboarding velocity | E5: RECOMMENDED FOR CORE: Free for standard setup diagnostics
A6: 2. Usage-Based Resolution Credits | B6: $0.50 / resolved query | C6: High Friction (Unpredictable bills for non-technical users) | D6: Direct cost recovery but penalizes users who need help | E6: NOT RECOMMENDED: Punishes confused non-technical users
A7: 3. Paid Plan Add-on (Cheerio Assist Pro) | B7: $19.00 / mo / business | C7: Low Friction for growing businesses needing custom flows | D7: Generates high-margin recurring SaaS ARR ($14.2K/mo) | E7: RECOMMENDED FOR PRO: Paid add-on for custom CRM & priority SLA
A9: Financial P&L for Option 3: 'Cheerio Assist Pro' Add-On Tier
A10: Parameter | B10: Formula / Value | C10: Monthly Amount | D10: Unit | E10: Analytical Rationale
A11: Total Addressable Active Businesses | B11: =Assumptions!B5 | C11: =Assumptions!B5 | D11: #,##0 | E11: Total customer base in Cheerio workspace
A12: Paid Pro Add-on Adoption Rate | B12: =Assumptions!B16 | C12: =Assumptions!B16 | D12: 0.0% | E12: Conservative 15% adoption rate (does not assume 100%)
A13: Paying Business Accounts | B13: =C11*C12 | C13: =C11*C12 | D13: #,##0 | E13: 750 businesses paying for enhanced Assist Pro workflows
A14: Monthly Add-on Subscription Price | B14: =Assumptions!B15 | C14: =Assumptions!B15 | D14: $#,##0.00 | E14: Proposed $19.00/month flat fee per account
A15: Gross Monthly Subscription Revenue | B15: =C13*C14 | C15: =C13*C14 | D15: $#,##0.00 | E15: 750 accounts * $19.00/month = $14,250.00 ARR driver
A16: Allocated Solution Operating Cost (AI + Infra) | B16: ='Running Cost'!D10 | C16: ='Running Cost'!D10 | D16: $#,##0.00 | E16: Total operating cost of Cheerio Assist (~$250.95/month)
A17: Monthly Gross Profit | B17: =C15-C16 | C17: =C15-C16 | D17: $#,##0.00 | E17: Monthly net contribution margin from Cheerio Assist Pro
A18: Gross Margin Percentage | B18: =C17/C15 | C18: =C17/C15 | D18: 0.0% | E18: Exceptional 98.2% gross margin due to ultra-efficient LLM tokens
A19: Break-Even Paying Business Accounts | B19: =C16/C14 | C19: =C16/C14 | D19: #,##0 | E19: Only 14 paying businesses needed to cover entire AI & infra cost!

Sheet Audit & Savings
A1: Cheerio Assist — Human Support Cost Savings & Governance Audit
A2: Quantifies net operational savings vs manual human support and defines 8 monthly audit thresholds.
A4: Financial Metric | B4: Formula / Source | C4: Monthly Figure ($) | D4: Annualized ($) | E4: Strategic Impact Summary
A5: Human Support Cost Without Solution (Status Quo) | B5: ='Volume & Resolution'!C5*Assumptions!B14 | C5: ='Volume & Resolution'!C5*Assumptions!B14 | D5: =C5*12 | E5: 4,000 inbound queries * $8.50/human ticket = $34,000/mo spend
A6: Residual Human Support Cost With Cheerio Assist | B6: ='Volume & Resolution'!C10*Assumptions!B14 | C6: ='Volume & Resolution'!C10*Assumptions!B14 | D6: =C6*12 | E6: 2,180 escalated/ineligible queries * $8.50/ticket = $18,530/mo spend
A7: Gross Monthly Human Labor Savings | B7: =C5-C6 | C7: =C5-C6 | D7: =C7*12 | E7: 1,820 tickets eliminated from human queues = $15,470/mo saved
A8: Total Operating Cost of Cheerio Assist | B8: ='Running Cost'!D10 | C8: ='Running Cost'!D10 | D8: =C8*12 | E8: AI tokens + cloud infrastructure = $250.95/mo
A9: Net Monthly Support Cost Savings | B9: =C7-C8 | C9: =C7-C8 | D9: =C9*12 | E9: Gross Labor Savings minus Solution Cost = $15,219.05/mo Net!
A10: Percentage Cost Reduction on Inbound Support | B10: =C9/C5 | C10: =C9/C5 | D10: N/A | E10: Net 44.8% reduction in total customer support operating expenditure
A11: ROI Multiple on AI Investment | B11: =C7/C8 | C11: =C7/C8 | D11: N/A | E11: Every $1.00 spent on Cheerio Assist saves $61.64 in human support labor!
A13: Monthly Engineering, Billing & Safety Audit Controls
A14: Audit Check | B14: Target Cadence | C14: Recommended Alert Threshold | D14: Remediation Action if Triggered | E14: Owner
A15: 1. AI Usage vs. Billed Customer Usage | B15: Monthly | C15: Variance > 5.0% between provider logs and internal counts | D15: Reconcile token telemetry; inspect gateway dropouts | E15: Product Analyst
A16: 2. Token Consumption & Provider Invoices | B16: Monthly / Weekly | C16: MoM token growth > 25% without corresponding user growth | D16: Audit prompt token bloat; prune vector context chunk size | E16: AI Engineer
A17: 3. Duplicate Usage Records / Loop Trap | B17: Daily Automated | C17: > 4 identical diagnostic queries from same user in 1 hour | D17: Break recursive loop; auto-escalate with pre-filled case | E17: AI Engineer
A18: 4. Failed or Repeated API Requests | B18: Real-Time / Daily | C18: Client retry failure rate > 8.0% | D18: Check Meta Cloud API webhook latency & status page | E18: DevOps / Support Eng
A19: 5. Unusual Cost per Resolution Spike | B19: Weekly | C19: Cost per automated resolution > $0.05 | D19: Inspect model fallback routing; ensure mini-tier routing | E19: AI Engineer
A20: 6. Escalation Rate Drift | B20: Weekly | C20: Escalation rate on eligible queries > 45.0% | D20: Review failed diagnostic paths; update decision tree rules | E20: Product Manager
A21: 7. Revenue & Subscription Churn | B21: Monthly | C21: Pro Add-on monthly churn > 5.0% | D21: Interview churning accounts; refine custom CRM integrations | E21: Product Manager
A22: 8. Gross Margin Degradation Floor | B22: Monthly | C22: Gross margin on Cheerio Assist Pro drops below 85.0% | D22: Review infrastructure allocations and token efficiency | E22: Product Analyst
